titiler/xarray/__init__.py
titiler/xarray/dependencies.py
titiler/xarray/extensions.py
titiler/xarray/factory.py
titiler/xarray/io.py
titiler/xarray/main.py
titiler/xarray/py.typed
titiler/xarray/templates/conformance.html
titiler/xarray/templates/header.html
titiler/xarray/templates/landing.html
titiler_xarray-1.0.2.dist-info/METADATA
titiler_xarray-1.0.2.dist-info/WHEEL
titiler_xarray-1.0.2.dist-info/licenses/LICENSE
titiler_xarray-1.0.2.dist-info/RECORD
