Metadata-Version: 2.4
Name: titiler-xarray
Version: 1.0.2
Summary: Xarray plugin for TiTiler.
Project-URL: Homepage, https://developmentseed.org/titiler/
Project-URL: Documentation, https://developmentseed.org/titiler/
Project-URL: Issues, https://github.com/developmentseed/titiler/issues
Project-URL: Source, https://github.com/developmentseed/titiler
Project-URL: Changelog, https://developmentseed.org/titiler/release-notes/
Author-email: Vincent Sarago <vincent@developmentseed.com>, Aimee Barciauskas <aimee@developmentseed.com>
License: MIT
License-File: LICENSE
Keywords: HDF,NetCDF,TiTiler,Xarray,Zarr
Classifier: Development Status :: 4 - Beta
Classifier: Intended Audience :: Information Technology
Classifier: Intended Audience :: Science/Research
Classifier: License :: OSI Approved :: MIT License
Classifier: Programming Language :: Python :: 3
Classifier: Programming Language :: Python :: 3.11
Classifier: Programming Language :: Python :: 3.12
Classifier: Programming Language :: Python :: 3.13
Classifier: Programming Language :: Python :: 3.14
Classifier: Topic :: Scientific/Engineering :: GIS
Requires-Python: >=3.11
Requires-Dist: obstore
Requires-Dist: rioxarray
Requires-Dist: titiler-core==1.0.2
Requires-Dist: xarray
Requires-Dist: zarr<4.0,>=3.1
Provides-Extra: fs
Requires-Dist: aiohttp; extra == 'fs'
Requires-Dist: fsspec; extra == 'fs'
Requires-Dist: gcsfs; extra == 'fs'
Requires-Dist: h5netcdf; extra == 'fs'
Requires-Dist: requests; extra == 'fs'
Requires-Dist: s3fs>=2025.2.0; extra == 'fs'
Provides-Extra: telemetry
Requires-Dist: opentelemetry-api; extra == 'telemetry'
Requires-Dist: opentelemetry-exporter-otlp; extra == 'telemetry'
Requires-Dist: opentelemetry-instrumentation-fastapi; extra == 'telemetry'
Requires-Dist: opentelemetry-instrumentation-logging; extra == 'telemetry'
Requires-Dist: opentelemetry-sdk; extra == 'telemetry'
